{
  "misaki": [
    {
      "question": "休日に何をしたい？って聞かれたら、あたしは迷わず…",
      "choices": ["一緒にスポーツ！", "家でゲーム", "図書館で読書"],
      "correct": 0,
      "comment": "体を動かすのが一番！一緒に走ろうよ！"
    },
    {
      "question": "あたしの好きなスイーツ、なんだと思う？",
      "choices": ["クレープ", "抹茶ケーキ", "チョコレートフォンデュ"],
      "correct": 0,
      "comment": "クレープ大好き！特にいちごクリーム！"
    },
    {
      "question": "デートするならどこがいい？",
      "choices": ["遊園地", "美術館", "高級レストラン"],
      "correct": 0,
      "comment": "遊園地！ジェットコースター何回でも乗りたい！"
    },
    {
      "question": "落ち込んでるあたしにかける言葉は？",
      "choices": ["一緒に走って気分転換しよう！", "一人にしてあげるね", "論理的に解決策を考えよう"],
      "correct": 0,
      "comment": "うん！走ったら元気出る！ありがと！"
    },
    {
      "question": "あたしが一番好きな季節はなんでしょう？",
      "choices": ["夏！海にプールに最高！", "秋の読書の季節", "冬のこたつ"],
      "correct": 0,
      "comment": "夏が一番！太陽の下で遊ぶのが最高なんだよね！"
    },
    {
      "question": "プレゼントをくれるなら何が嬉しい？",
      "choices": ["新しいスニーカー", "アクセサリー", "本"],
      "correct": 0,
      "comment": "やった！新しい靴で一緒に走ろう！"
    },
    {
      "question": "あたしの朝のルーティン、どれだと思う？",
      "choices": ["朝ランニング", "ゆっくり朝食", "ギリギリまで寝る"],
      "correct": 0,
      "comment": "毎朝走るの！気持ちいいんだよ～！"
    },
    {
      "question": "映画を観るならどのジャンル？",
      "choices": ["スポーツ・アクション映画", "ホラー映画", "恋愛映画"],
      "correct": 0,
      "comment": "アクション映画最高！手に汗握る感じがたまらない！"
    },
    {
      "question": "あたしの将来の夢はなんでしょう？",
      "choices": ["体育の先生", "科学者", "パティシエ"],
      "correct": 0,
      "comment": "体育の先生になって、みんなにスポーツの楽しさを教えたい！"
    },
    {
      "question": "あたしが一番大切にしてることは？",
      "choices": ["仲間と一緒に全力で楽しむこと", "一人の時間を大切にすること", "計画通りに物事を進めること"],
      "correct": 0,
      "comment": "みんなと一緒だから楽しいんだよ！あなたとも…ね？"
    },
    {
      "question": "お弁当に入ってたら嬉しいおかずは？",
      "choices": ["からあげ", "サラダ", "煮物"],
      "correct": 0,
      "comment": "からあげ最高！いくらでも食べられる！"
    },
    {
      "question": "あたしが好きな動物はなんでしょう？",
      "choices": ["犬", "猫", "うさぎ"],
      "correct": 0,
      "comment": "犬！一緒にお散歩できるし、元気いっぱいなところが好き！"
    }
  ],
  "rin": [
    {
      "question": "私の好きな飲み物は何かしら？",
      "choices": ["ダージリンティー", "コーラ", "抹茶ラテ"],
      "correct": 0,
      "comment": "ダージリンのファーストフラッシュが最高よ。"
    },
    {
      "question": "私と過ごすなら、どんな時間がいいかしら？",
      "choices": ["静かな図書館で読書", "カラオケで盛り上がる", "スポーツ観戦"],
      "correct": 0,
      "comment": "本に囲まれた静かな空間…理想的ね。"
    },
    {
      "question": "私にプレゼントをくれるなら？",
      "choices": ["美しい装丁の本", "ぬいぐるみ", "スポーツ用品"],
      "correct": 0,
      "comment": "本は何冊あっても足りないわ。センスがいいのね。"
    },
    {
      "question": "私が落ち込んでいたら、どうする？",
      "choices": ["そっと隣にいて、話を聞く", "無理やり外に連れ出す", "面白い動画を見せる"],
      "correct": 0,
      "comment": "…ありがとう。あなたの静かな優しさが、心地いいわ。"
    },
    {
      "question": "私の好きな天体現象は？",
      "choices": ["流星群", "花火大会", "日食"],
      "correct": 0,
      "comment": "流星群の夜は特別…一緒に見てくれる？"
    },
    {
      "question": "私の好きな音楽のジャンルは？",
      "choices": ["クラシック", "ロック", "アイドルソング"],
      "correct": 0,
      "comment": "ショパンのノクターンが特に好きよ。"
    },
    {
      "question": "テスト前の私はどんな感じだと思う？",
      "choices": ["余裕を持って計画的に勉強", "徹夜で詰め込む", "全く勉強しない"],
      "correct": 0,
      "comment": "計画的に準備するのは当然のことよ。"
    },
    {
      "question": "私と食事に行くなら、どんなお店がいいかしら？",
      "choices": ["落ち着いた雰囲気のカフェ", "にぎやかな居酒屋", "ファストフード"],
      "correct": 0,
      "comment": "静かなカフェで、ゆっくり話したいわ。"
    },
    {
      "question": "私が一番嫌いなことは何だと思う？",
      "choices": ["いい加減な嘘をつくこと", "静かにしていること", "勉強すること"],
      "correct": 0,
      "comment": "不誠実なことは許せないの。正直でいてね。"
    },
    {
      "question": "私があなたに求めることは？",
      "choices": ["知的な会話ができること", "いつも盛り上げてくれること", "たくさんプレゼントをくれること"],
      "correct": 0,
      "comment": "あなたとの会話は…心が満たされるわ。"
    },
    {
      "question": "私の好きな季節は？",
      "choices": ["秋", "夏", "春"],
      "correct": 0,
      "comment": "秋の夜長に読書…最高の季節よ。"
    },
    {
      "question": "私の休日の過ごし方は？",
      "choices": ["お気に入りの本と紅茶で過ごす", "友達と買い物", "一日中寝る"],
      "correct": 0,
      "comment": "窓辺で紅茶を飲みながら本を読む…至福の時間ね。"
    }
  ],
  "hinata": [
    {
      "question": "わたしが得意なお料理はなんでしょう？",
      "choices": ["手作りクッキー", "激辛カレー", "お刺身"],
      "correct": 0,
      "comment": "えへへ、クッキー焼くの大好きなんです。今度一緒に作りましょう？"
    },
    {
      "question": "わたしが一番好きなお花は？",
      "choices": ["ひまわり", "バラ", "ユリ"],
      "correct": 0,
      "comment": "ひまわりみたいに明るく元気でいたいんです。"
    },
    {
      "question": "わたしにプレゼントしてくれるなら？",
      "choices": ["かわいい植木鉢", "ゲームソフト", "スポーツ用品"],
      "correct": 0,
      "comment": "わぁ！お花育てるの大好き！嬉しいです～！"
    },
    {
      "question": "わたしが泣いてたら、どうしてくれる？",
      "choices": ["優しく頭をなでる", "「泣くな」と言う", "理由を問い詰める"],
      "correct": 0,
      "comment": "…ありがとう。その優しさが、とっても温かいです。"
    },
    {
      "question": "一緒にお出かけするならどこがいい？",
      "choices": ["動物園", "ゲームセンター", "ライブハウス"],
      "correct": 0,
      "comment": "動物さんたち、みんなかわいいですよね～！"
    },
    {
      "question": "わたしの好きな動物は？",
      "choices": ["うさぎ", "蛇", "カブトムシ"],
      "correct": 0,
      "comment": "うさぎさん、もふもふでかわいいんです～！"
    },
    {
      "question": "わたしが苦手なものはなんでしょう？",
      "choices": ["辛い食べ物", "甘いもの", "野菜"],
      "correct": 0,
      "comment": "辛いの食べると涙が出ちゃうんです…えぅ。"
    },
    {
      "question": "わたしの夢はなんだと思いますか？",
      "choices": ["小さなケーキ屋さん", "アスリート", "プログラマー"],
      "correct": 0,
      "comment": "みんなが笑顔になるケーキを作りたいんです！"
    },
    {
      "question": "わたしが一番大切にしてることは？",
      "choices": ["みんなの笑顔", "自分の成績", "お金"],
      "correct": 0,
      "comment": "誰かが笑ってくれたら、わたしも幸せなんです。"
    },
    {
      "question": "わたしとお家で過ごすなら何したい？",
      "choices": ["一緒にお菓子作り", "ゲーム大会", "映画鑑賞"],
      "correct": 0,
      "comment": "一緒にお菓子作り、楽しそう！何作りましょうか？"
    },
    {
      "question": "わたしの好きな季節は？",
      "choices": ["春", "冬", "秋"],
      "correct": 0,
      "comment": "春はお花がいっぱい咲いて、あたたかくて…大好きです！"
    },
    {
      "question": "わたしが朝起きて最初にすることは？",
      "choices": ["ベランダのお花に水やり", "SNSチェック", "二度寝"],
      "correct": 0,
      "comment": "お花さんたち、おはようって声かけるんです。えへへ。"
    }
  ]
}
